PyGnuTLS/__init__.py
PyGnuTLS/__init__.pyi
PyGnuTLS/connection.py
PyGnuTLS/connection.pyi
PyGnuTLS/crypto.py
PyGnuTLS/crypto.pyi
PyGnuTLS/errors.py
PyGnuTLS/errors.pyi
PyGnuTLS/py.typed
PyGnuTLS/library/__init__.py
PyGnuTLS/library/__init__.pyi
PyGnuTLS/library/constants.py
PyGnuTLS/library/constants.pyi
PyGnuTLS/library/errors.py
PyGnuTLS/library/errors.pyi
PyGnuTLS/library/functions.py
PyGnuTLS/library/functions.pyi
PyGnuTLS/library/types.py
PyGnuTLS/library/types.pyi
PyGnuTLS/tests/__init__.py
PyGnuTLS/tests/test_asymmetric.py
PyGnuTLS/tests/test_cert_crl.py
PyGnuTLS/tests/test_pkcs7.py
PyGnuTLS-0.1.4.dist-info/LICENSE
PyGnuTLS-0.1.4.dist-info/METADATA
PyGnuTLS-0.1.4.dist-info/WHEEL
PyGnuTLS-0.1.4.dist-info/top_level.txt
PyGnuTLS-0.1.4.dist-info/RECORD
