Metadata-Version: 2.1
Name: PyGnuTLS
Version: 0.1.4
Summary: Python wrapper for the GnuTLS library
Home-page: https://github.com/hughsie/PyGnuTLS
Author: Richard Hughes
Author-email: richard@hughsie.com
License: LGPL
Platform: Platform Independent
Classifier: Programming Language :: Python :: 3
Classifier: License :: OSI Approved :: GNU Library or Lesser General Public License (LGPL)
Classifier: Operating System :: OS Independent
Classifier: Intended Audience :: Developers
Requires-Python: >=3.5
License-File: LICENSE
